{
	"miniprogramRoot": "miniprogram/",
	"cloudfunctionRoot": "cloudfunctions/",
	"setting": {
		"urlCheck": true,
		"es6": true,
		"postcss": true,
		"minified": true,
		"newFeature": true,
		"enhance": true
	},
	"appid": "wx8939d6abe6252f2d",
	"projectname": "wechat-music",
	"libVersion": "2.8.1",
	"simulatorType": "wechat",
	"simulatorPluginLibVersion": {},
	"condition": {
		"search": {
			"current": -1,
			"list": []
		},
		"conversation": {
			"current": -1,
			"list": []
		},
		"plugin": {
			"current": -1,
			"list": []
		},
		"game": {
			"list": []
		},
		"gamePlugin": {
			"current": -1,
			"list": []
		},
		"miniprogram": {
			"current": -1,
			"list": [
				{
					"id": -1,
					"name": "db guide",
					"pathName": "pages/databaseGuide/databaseGuide",
					"query": ""
				},
				{
					"id": 1,
					"name": "muscilist",
					"pathName": "pages/musiclist/musiclist",
					"query": "playlistId=2168895862",
					"scene": null
				},
				{
					"id": -1,
					"name": "blog",
					"pathName": "pages/blog/blog",
					"query": "",
					"scene": null
				},
				{
					"id": -1,
					"name": "blog-edit",
					"pathName": "pages/blog-edit/blog-edit",
					"query": "nickName=\"幻听\"&avatarUrl=\"https://wx.qlogo.cn/mmopen/vi_32/Q0j4TwGTfTLBxlibE…XWRJLlXgop63GCryHEL4CnxL8rQNd5zqiayLyHw4lPmhA/132\"}",
					"scene": null
				},
				{
					"id": -1,
					"name": "我的",
					"pathName": "pages/profile/profile",
					"scene": null
				}
			]
		}
	}
}